polyvirt/__init__.py
polyvirt/decorators.py
polyvirt/environment_registry.py
polyvirt/main.py
polyvirt/utils.py
polyvirt/managers/__init__.py
polyvirt/managers/base_manager.py
polyvirt/managers/conda_manager.py
polyvirt/managers/venv_manager.py
polyvirt/managers/virtualenv_manager.py
polyvirt-0.1.0.dist-info/LICENSE
polyvirt-0.1.0.dist-info/METADATA
polyvirt-0.1.0.dist-info/WHEEL
polyvirt-0.1.0.dist-info/entry_points.txt
polyvirt-0.1.0.dist-info/top_level.txt
polyvirt-0.1.0.dist-info/RECORD
