Metadata-Version: 2.2
Name: polyvirt
Version: 0.1.0
Summary: A CLI tool to manage Python virtual environments across multiple managers.
Author: Dayton Jones
Requires-Python: >=3.7
License-File: LICENSE
Requires-Dist: colored
Requires-Dist: tqdm
Dynamic: author
Dynamic: description
Dynamic: description-content-type
Dynamic: requires-dist
Dynamic: requires-python
Dynamic: summary
